instaharvest/__init__.py
instaharvest/base.py
instaharvest/comment_scraper.py
instaharvest/comments_export.py
instaharvest/config.py
instaharvest/diagnostics.py
instaharvest/error_handler.py
instaharvest/excel_export.py
instaharvest/exceptions.py
instaharvest/exporter.py
instaharvest/exporters.py
instaharvest/follow.py
instaharvest/followers.py
instaharvest/logger.py
instaharvest/message.py
instaharvest/models.py
instaharvest/network_client.py
instaharvest/orchestrator.py
instaharvest/parallel_scraper.py
instaharvest/parser.py
instaharvest/performance.py
instaharvest/post_data.py
instaharvest/post_links.py
instaharvest/profile.py
instaharvest/reel_data.py
instaharvest/reel_links.py
instaharvest/security.py
instaharvest/session_utils.py
instaharvest/shared_browser.py
instaharvest-2.6.0.dist-info/licenses/LICENSE
instaharvest-2.6.0.dist-info/METADATA
instaharvest-2.6.0.dist-info/WHEEL
instaharvest-2.6.0.dist-info/top_level.txt
instaharvest-2.6.0.dist-info/RECORD
