Metadata-Version: 2.4
Name: instaharvest
Version: 2.6.0
Summary: Professional Instagram data collection toolkit with automation features
Home-page: https://github.com/mpython77/insta-harvester
Author: Muydinov Doston
Author-email: kelajak054@gmail.com
Project-URL: Bug Reports, https://github.com/mpython77/insta-harvester/issues
Project-URL: Source, https://github.com/mpython77/insta-harvester
Project-URL: Documentation, https://github.com/mpython77/insta-harvester#readme
Keywords: instagram,scraper,automation,data-collection,social-media,instagram-api,instagram-bot,followers,instagram-scraper,web-scraping,playwright
Classifier: Development Status :: 4 - Beta
Classifier: Intended Audience :: Developers
Classifier: Topic :: Software Development :: Libraries :: Python Modules
Classifier: Topic :: Internet :: WWW/HTTP :: Dynamic Content
Classifier: Programming Language :: Python :: 3
Classifier: Programming Language :: Python :: 3.8
Classifier: Programming Language :: Python :: 3.9
Classifier: Programming Language :: Python :: 3.10
Classifier: Programming Language :: Python :: 3.11
Classifier: Operating System :: OS Independent
Requires-Python: >=3.8
License-File: LICENSE
Requires-Dist: playwright>=1.40.0
Requires-Dist: pandas>=2.0.0
Requires-Dist: openpyxl>=3.1.0
Requires-Dist: beautifulsoup4>=4.12.0
Requires-Dist: lxml>=4.9.0
Requires-Dist: psutil>=5.9.0
Requires-Dist: curl_cffi>=0.7.4
Requires-Dist: pydantic>=2.0.0
Requires-Dist: fake-useragent>=1.5.0
Requires-Dist: httpx>=0.27.0
Provides-Extra: dev
Requires-Dist: pytest>=7.0.0; extra == "dev"
Requires-Dist: pytest-cov>=4.0.0; extra == "dev"
Requires-Dist: black>=23.0.0; extra == "dev"
Requires-Dist: flake8>=6.0.0; extra == "dev"
Requires-Dist: mypy>=1.0.0; extra == "dev"
Dynamic: author
Dynamic: author-email
Dynamic: classifier
Dynamic: description
Dynamic: description-content-type
Dynamic: home-page
Dynamic: keywords
Dynamic: license-file
Dynamic: project-url
Dynamic: provides-extra
Dynamic: requires-dist
Dynamic: requires-python
Dynamic: summary
